rpycocotools-0.0.7.dist-info/METADATA
rpycocotools-0.0.7.dist-info/WHEEL
rpycocotools/anns.py
rpycocotools/mask.py
rpycocotools/__init__.py
rpycocotools/_rpycocotools.cpython-312-s390x-linux-gnu.so
rpycocotools-0.0.7.dist-info/RECORD
