Metadata-Version: 2.1
Name: rpycocotools
Version: 0.0.7
Classifier: License :: OSI Approved :: MIT License
Classifier: Programming Language :: Python :: 3
Classifier: Programming Language :: Python :: 3 :: Only
Classifier: Programming Language :: Python :: 3.8
Classifier: Programming Language :: Python :: 3.9
Classifier: Programming Language :: Python :: 3.10
Classifier: Operating System :: OS Independent
Classifier: Intended Audience :: Developers
Classifier: Programming Language :: Rust
Classifier: Programming Language :: Python :: Implementation :: CPython
Classifier: Programming Language :: Python :: Implementation :: PyPy
Requires-Dist: numpy >=1.21.0
Requires-Dist: rpycocotools-stubs
Requires-Dist: maturin ; extra == 'build'
Requires-Dist: pytest ; extra == 'test'
Requires-Dist: hypothesis ; extra == 'test'
Requires-Dist: pytest-benchmark ; extra == 'benchmarks'
Requires-Dist: pycocotools ; extra == 'benchmarks'
Requires-Dist: pycocotools-stubs ; extra == 'benchmarks'
Requires-Dist: pip-tools ; extra == 'dev'
Requires-Dist: ruff ; extra == 'dev'
Requires-Dist: pyright ; extra == 'dev'
Requires-Dist: sphinx ; extra == 'doc'
Requires-Dist: sphinx-rtd-theme ; extra == 'doc'
Requires-Dist: sphinx-hoverxref ; extra == 'doc'
Requires-Dist: sphinx-codeautolink ; extra == 'doc'
Requires-Dist: flake8 >=5.0.4, <6.0 ; extra == 'flake8'
Requires-Dist: flake8-bugbear >=23.3.12, <24.0 ; extra == 'flake8'
Requires-Dist: flake8-builtins >=2.1.0, <3.0 ; extra == 'flake8'
Requires-Dist: flake8-comprehensions >=3.12.0, <4.0 ; extra == 'flake8'
Requires-Dist: flake8-docstrings >=1.7.0, <2.0 ; extra == 'flake8'
Requires-Dist: flake8-quotes >=3.3.2, <4 ; extra == 'flake8'
Requires-Dist: pep8-naming >=0.13.3 ; extra == 'flake8'
Requires-Dist: flake8-import-order >=0.18.2 ; extra == 'flake8'
Requires-Dist: flake8-noqa >=1.3.1, <2 ; extra == 'flake8'
Requires-Dist: flake8-broken-line >=0.6.0 ; extra == 'flake8'
Requires-Dist: flake8-commas >=2.1.0, <3.0 ; extra == 'flake8'
Requires-Dist: Flake8-pyproject >=1.2.3, <2 ; extra == 'flake8'
Provides-Extra: build
Provides-Extra: test
Provides-Extra: benchmarks
Provides-Extra: dev
Provides-Extra: doc
Provides-Extra: flake8
Summary: Package providing utilities to load, manipulate, convert and visualize COCO format datasets.
Keywords: COCO,COCO dataset
Author: Bagard Hoel
License: MIT
Requires-Python: >=3.8
Project-URL: Source Code, https://github.com/hoel-bagard/rust_coco_tools
